tiramisu_api/__init__.py
tiramisu_api/api.py
tiramisu_api/error.py
tiramisu_api/i18n.py
tiramisu_api/setting.py
tiramisu_api-0.5.dist-info/LICENSE
tiramisu_api-0.5.dist-info/METADATA
tiramisu_api-0.5.dist-info/WHEEL
tiramisu_api-0.5.dist-info/top_level.txt
tiramisu_api-0.5.dist-info/RECORD
