Metadata-Version: 2.1
Name: tiramisu-api
Version: 0.5
Summary: a subset of Tiramisu API
Home-page: https://framagit.org/tiramisu/tiramisu-api-python
Author: Tiramisu's team
Author-email: gnunux@gnunux.info
License: GNU Library or Lesser General Public License (LGPL)
Platform: UNKNOWN
Classifier: Programming Language :: Python :: 3
Classifier: License :: OSI Approved :: GNU Library or Lesser General Public License (LGPL)
Classifier: Operating System :: OS Independent
Classifier: Natural Language :: English
Classifier: Natural Language :: French
